{
  "country": "Israel",
  "age": "35-44 years old",
  "max_used": 0.21744791666666666,
  "max_interested": 0.22131147540983606,
  "years": {
    "2016": [
      {
        "language": "C",
        "avg_salary": 87000.0,
        "execution_model": "compiled",
        "memory_management": "manual",
        "used": 0.058394160583941604,
        "interested": 0.01639344262295082
      },
      {
        "language": "C#",
        "avg_salary": 84285.71428571429,
        "execution_model": "compiled",
        "memory_management": "gc",
        "used": 0.145985401459854,
        "interested": 0.11475409836065574
      },
      {
        "language": "C++",
        "avg_salary": 92333.33333333333,
        "execution_model": "compiled",
        "memory_management": "manual",
        "used": 0.072992700729927,
        "interested": 0.05737704918032787
      },
      {
        "language": "Clojure",
        "avg_salary": 85000.0,
        "execution_model": "interpreted",
        "memory_management": "gc",
        "used": 0.014598540145985401,
        "interested": 0.02459016393442623
      },
      {
        "language": "CoffeeScript",
        "avg_salary": 65000.0,
        "execution_model": "interpreted",
        "memory_management": "gc",
        "used": 0.0,
        "interested": 0.00819672131147541
      },
      {
        "language": "Dart",
        "avg_salary": 55000.0,
        "execution_model": "compiled",
        "memory_management": "gc",
        "used": 0.0,
        "interested": 0.00819672131147541
      },
      {
        "language": "F#",
        "avg_salary": 68333.33333333333,
        "execution_model": "compiled",
        "memory_management": "gc",
        "used": 0.0,
        "interested": 0.02459016393442623
      },
      {
        "language": "Go",
        "avg_salary": 78333.33333333333,
        "execution_model": "compiled",
        "memory_management": "gc",
        "used": 0.0,
        "interested": 0.03278688524590164
      },
      {
        "language": "Haskell",
        "avg_salary": 98333.33333333333,
        "execution_model": "compiled",
        "memory_management": "gc",
        "used": 0.0,
        "interested": 0.02459016393442623
      },
      {
        "language": "Java",
        "avg_salary": 109400.0,
        "execution_model": "compiled",
        "memory_management": "gc",
        "used": 0.1386861313868613,
        "interested": 0.11475409836065574
      },
      {
        "language": "JavaScript",
        "avg_salary": 79222.22222222222,
        "execution_model": "interpreted",
        "memory_management": "gc",
        "used": 0.19708029197080293,
        "interested": 0.22131147540983606
      },
      {
        "language": "Objective-C",
        "avg_salary": 137000.0,
        "execution_model": "compiled",
        "memory_management": "manual",
        "used": 0.021897810218978103,
        "interested": 0.01639344262295082
      },
      {
        "language": "PHP",
        "avg_salary": 69444.44444444444,
        "execution_model": "interpreted",
        "memory_management": "gc",
        "used": 0.043795620437956206,
        "interested": 0.03278688524590164
      },
      {
        "language": "Perl",
        "avg_salary": 85000.0,
        "execution_model": "interpreted",
        "memory_management": "gc",
        "used": 0.0072992700729927005,
        "interested": 0.0
      },
      {
        "language": "Python",
        "avg_salary": 91875.0,
        "execution_model": "interpreted",
        "memory_management": "gc",
        "used": 0.08759124087591241,
        "interested": 0.08196721311475409
      },
      {
        "language": "R",
        "avg_salary": 52500.0,
        "execution_model": "interpreted",
        "memory_management": "gc",
        "used": 0.014598540145985401,
        "interested": 0.03278688524590164
      },
      {
        "language": "Ruby",
        "avg_salary": 83333.33333333333,
        "execution_model": "interpreted",
        "memory_management": "gc",
        "used": 0.021897810218978103,
        "interested": 0.02459016393442623
      },
      {
        "language": "Rust",
        "avg_salary": 98333.33333333333,
        "execution_model": "compiled",
        "memory_management": "manual",
        "used": 0.0,
        "interested": 0.03278688524590164
      },
      {
        "language": "SQL",
        "avg_salary": 87916.66666666667,
        "execution_model": "interpreted",
        "memory_management": "na",
        "used": 0.1678832116788321,
        "interested": 0.03278688524590164
      },
      {
        "language": "Scala",
        "avg_salary": 96666.66666666667,
        "execution_model": "compiled",
        "memory_management": "gc",
        "used": 0.0,
        "interested": 0.07377049180327869
      },
      {
        "language": "Swift",
        "avg_salary": 135000.0,
        "execution_model": "compiled",
        "memory_management": "gc",
        "used": 0.0072992700729927005,
        "interested": 0.02459016393442623
      }
    ],
    "2018": [
      {
        "language": "C",
        "avg_salary": 142557.58,
        "execution_model": "compiled",
        "memory_management": "manual",
        "used": 0.06870229007633588,
        "interested": 0.04038461538461539
      },
      {
        "language": "C#",
        "avg_salary": 98314.31506849315,
        "execution_model": "compiled",
        "memory_management": "gc",
        "used": 0.09618320610687023,
        "interested": 0.08461538461538462
      },
      {
        "language": "C++",
        "avg_salary": 128732.53623188406,
        "execution_model": "compiled",
        "memory_management": "manual",
        "used": 0.07786259541984733,
        "interested": 0.07692307692307693
      },
      {
        "language": "Clojure",
        "avg_salary": 99706.8,
        "execution_model": "interpreted",
        "memory_management": "gc",
        "used": 0.0030534351145038168,
        "interested": 0.01730769230769231
      },
      {
        "language": "CoffeeScript",
        "avg_salary": 174555.25,
        "execution_model": "interpreted",
        "memory_management": "gc",
        "used": 0.007633587786259542,
        "interested": 0.0
      },
      {
        "language": "F#",
        "avg_salary": 84258.66666666667,
        "execution_model": "compiled",
        "memory_management": "gc",
        "used": 0.0015267175572519084,
        "interested": 0.011538461538461539
      },
      {
        "language": "Go",
        "avg_salary": 102462.38095238095,
        "execution_model": "compiled",
        "memory_management": "gc",
        "used": 0.024427480916030534,
        "interested": 0.08269230769230769
      },
      {
        "language": "Haskell",
        "avg_salary": 109419.42857142857,
        "execution_model": "compiled",
        "memory_management": "gc",
        "used": 0.0030534351145038168,
        "interested": 0.015384615384615385
      },
      {
        "language": "Java",
        "avg_salary": 139775.54022988505,
        "execution_model": "compiled",
        "memory_management": "gc",
        "used": 0.12213740458015267,
        "interested": 0.10384615384615385
      },
      {
        "language": "JavaScript",
        "avg_salary": 101880.33333333333,
        "execution_model": "interpreted",
        "memory_management": "gc",
        "used": 0.16946564885496182,
        "interested": 0.14615384615384616
      },
      {
        "language": "Objective-C",
        "avg_salary": 103129.5,
        "execution_model": "compiled",
        "memory_management": "manual",
        "used": 0.013740458015267175,
        "interested": 0.0057692307692307696
      },
      {
        "language": "PHP",
        "avg_salary": 84847.88461538461,
        "execution_model": "interpreted",
        "memory_management": "gc",
        "used": 0.0549618320610687,
        "interested": 0.01730769230769231
      },
      {
        "language": "Perl",
        "avg_salary": 137825.41666666666,
        "execution_model": "interpreted",
        "memory_management": "gc",
        "used": 0.016793893129770993,
        "interested": 0.011538461538461539
      },
      {
        "language": "Python",
        "avg_salary": 131925.1238938053,
        "execution_model": "interpreted",
        "memory_management": "gc",
        "used": 0.1297709923664122,
        "interested": 0.15576923076923077
      },
      {
        "language": "R",
        "avg_salary": 222859.82352941178,
        "execution_model": "interpreted",
        "memory_management": "gc",
        "used": 0.01984732824427481,
        "interested": 0.019230769230769232
      },
      {
        "language": "Ruby",
        "avg_salary": 91587.85714285714,
        "execution_model": "interpreted",
        "memory_management": "gc",
        "used": 0.01984732824427481,
        "interested": 0.011538461538461539
      },
      {
        "language": "Rust",
        "avg_salary": 102032.625,
        "execution_model": "compiled",
        "memory_management": "manual",
        "used": 0.004580152671755725,
        "interested": 0.03076923076923077
      },
      {
        "language": "SQL",
        "avg_salary": 112847.02325581395,
        "execution_model": "interpreted",
        "memory_management": "na",
        "used": 0.1297709923664122,
        "interested": 0.08653846153846154
      },
      {
        "language": "Scala",
        "avg_salary": 162222.88,
        "execution_model": "compiled",
        "memory_management": "gc",
        "used": 0.021374045801526718,
        "interested": 0.051923076923076926
      },
      {
        "language": "Swift",
        "avg_salary": 167805.15789473685,
        "execution_model": "compiled",
        "memory_management": "gc",
        "used": 0.015267175572519083,
        "interested": 0.03076923076923077
      }
    ],
    "2019": [
      {
        "language": "C",
        "avg_salary": 118655.6875,
        "execution_model": "compiled",
        "memory_management": "manual",
        "used": 0.0563564875491481,
        "interested": 0.040498442367601244
      },
      {
        "language": "C#",
        "avg_salary": 104935.02409638555,
        "execution_model": "compiled",
        "memory_management": "gc",
        "used": 0.09043250327653997,
        "interested": 0.0763239875389408
      },
      {
        "language": "C++",
        "avg_salary": 125223.26923076923,
        "execution_model": "compiled",
        "memory_management": "manual",
        "used": 0.06946264744429882,
        "interested": 0.06853582554517133
      },
      {
        "language": "Clojure",
        "avg_salary": 140416.0,
        "execution_model": "interpreted",
        "memory_management": "gc",
        "used": 0.003931847968545216,
        "interested": 0.01557632398753894
      },
      {
        "language": "Dart",
        "avg_salary": 111147.84615384616,
        "execution_model": "compiled",
        "memory_management": "gc",
        "used": 0.005242463958060288,
        "interested": 0.017133956386292833
      },
      {
        "language": "F#",
        "avg_salary": 72990.0,
        "execution_model": "compiled",
        "memory_management": "gc",
        "used": 0.002621231979030144,
        "interested": 0.00778816199376947
      },
      {
        "language": "Go",
        "avg_salary": 121086.1914893617,
        "execution_model": "compiled",
        "memory_management": "gc",
        "used": 0.02490170380078637,
        "interested": 0.08411214953271028
      },
      {
        "language": "Java",
        "avg_salary": 108250.75961538461,
        "execution_model": "compiled",
        "memory_management": "gc",
        "used": 0.12057667103538663,
        "interested": 0.09345794392523364
      },
      {
        "language": "JavaScript",
        "avg_salary": 109755.86263736263,
        "execution_model": "interpreted",
        "memory_management": "gc",
        "used": 0.1913499344692005,
        "interested": 0.1791277258566978
      },
      {
        "language": "Objective-C",
        "avg_salary": 113373.58823529411,
        "execution_model": "compiled",
        "memory_management": "manual",
        "used": 0.019659239842726082,
        "interested": 0.00778816199376947
      },
      {
        "language": "PHP",
        "avg_salary": 88846.97368421052,
        "execution_model": "interpreted",
        "memory_management": "gc",
        "used": 0.04456094364351245,
        "interested": 0.02336448598130841
      },
      {
        "language": "Python",
        "avg_salary": 116413.80645161291,
        "execution_model": "interpreted",
        "memory_management": "gc",
        "used": 0.13892529488859764,
        "interested": 0.1542056074766355
      },
      {
        "language": "R",
        "avg_salary": 110189.95454545454,
        "execution_model": "interpreted",
        "memory_management": "gc",
        "used": 0.015727391874180863,
        "interested": 0.020249221183800622
      },
      {
        "language": "Ruby",
        "avg_salary": 95367.96153846153,
        "execution_model": "interpreted",
        "memory_management": "gc",
        "used": 0.023591087811271297,
        "interested": 0.02336448598130841
      },
      {
        "language": "Rust",
        "avg_salary": 108236.66666666667,
        "execution_model": "compiled",
        "memory_management": "manual",
        "used": 0.007863695937090432,
        "interested": 0.03115264797507788
      },
      {
        "language": "SQL",
        "avg_salary": 98313.25409836066,
        "execution_model": "interpreted",
        "memory_management": "na",
        "used": 0.13761467889908258,
        "interested": 0.09968847352024922
      },
      {
        "language": "Scala",
        "avg_salary": 110298.03571428571,
        "execution_model": "compiled",
        "memory_management": "gc",
        "used": 0.027522935779816515,
        "interested": 0.03115264797507788
      },
      {
        "language": "Swift",
        "avg_salary": 110766.86363636363,
        "execution_model": "compiled",
        "memory_management": "gc",
        "used": 0.019659239842726082,
        "interested": 0.0264797507788162
      }
    ],
    "2020": [
      {
        "language": "C",
        "avg_salary": 133812.05714285714,
        "execution_model": "compiled",
        "memory_management": "manual",
        "used": 0.057279236276849645,
        "interested": 0.043010752688172046
      },
      {
        "language": "C#",
        "avg_salary": 108363.62962962964,
        "execution_model": "compiled",
        "memory_management": "gc",
        "used": 0.0954653937947494,
        "interested": 0.07258064516129033
      },
      {
        "language": "C++",
        "avg_salary": 135464.0,
        "execution_model": "compiled",
        "memory_management": "manual",
        "used": 0.07637231503579953,
        "interested": 0.07526881720430108
      },
      {
        "language": "Dart",
        "avg_salary": 125962.4,
        "execution_model": "compiled",
        "memory_management": "gc",
        "used": 0.00477326968973747,
        "interested": 0.010752688172043012
      },
      {
        "language": "Go",
        "avg_salary": 159589.0,
        "execution_model": "compiled",
        "memory_management": "gc",
        "used": 0.031026252983293555,
        "interested": 0.07526881720430108
      },
      {
        "language": "Haskell",
        "avg_salary": 157602.0,
        "execution_model": "compiled",
        "memory_management": "gc",
        "used": 0.0,
        "interested": 0.008064516129032258
      },
      {
        "language": "Java",
        "avg_salary": 140105.6923076923,
        "execution_model": "compiled",
        "memory_management": "gc",
        "used": 0.0954653937947494,
        "interested": 0.06989247311827956
      },
      {
        "language": "JavaScript",
        "avg_salary": 130307.71296296296,
        "execution_model": "interpreted",
        "memory_management": "gc",
        "used": 0.19331742243436753,
        "interested": 0.18010752688172044
      },
      {
        "language": "Objective-C",
        "avg_salary": 160871.2,
        "execution_model": "compiled",
        "memory_management": "manual",
        "used": 0.011933174224343675,
        "interested": 0.005376344086021506
      },
      {
        "language": "PHP",
        "avg_salary": 105110.23076923077,
        "execution_model": "interpreted",
        "memory_management": "gc",
        "used": 0.0477326968973747,
        "interested": 0.013440860215053764
      },
      {
        "language": "Perl",
        "avg_salary": 139799.0,
        "execution_model": "interpreted",
        "memory_management": "gc",
        "used": 0.007159904534606206,
        "interested": 0.002688172043010753
      },
      {
        "language": "Python",
        "avg_salary": 146765.9898989899,
        "execution_model": "interpreted",
        "memory_management": "gc",
        "used": 0.15990453460620524,
        "interested": 0.18010752688172044
      },
      {
        "language": "R",
        "avg_salary": 129861.2,
        "execution_model": "interpreted",
        "memory_management": "gc",
        "used": 0.011933174224343675,
        "interested": 0.021505376344086023
      },
      {
        "language": "Ruby",
        "avg_salary": 144757.81818181818,
        "execution_model": "interpreted",
        "memory_management": "gc",
        "used": 0.014319809069212411,
        "interested": 0.016129032258064516
      },
      {
        "language": "Rust",
        "avg_salary": 155073.1739130435,
        "execution_model": "compiled",
        "memory_management": "manual",
        "used": 0.011933174224343675,
        "interested": 0.07258064516129033
      },
      {
        "language": "SQL",
        "avg_salary": 159514.6794871795,
        "execution_model": "interpreted",
        "memory_management": "na",
        "used": 0.15035799522673032,
        "interested": 0.11290322580645161
      },
      {
        "language": "Scala",
        "avg_salary": 153446.7142857143,
        "execution_model": "compiled",
        "memory_management": "gc",
        "used": 0.016706443914081145,
        "interested": 0.01881720430107527
      },
      {
        "language": "Swift",
        "avg_salary": 141424.44444444444,
        "execution_model": "compiled",
        "memory_management": "gc",
        "used": 0.014319809069212411,
        "interested": 0.021505376344086023
      }
    ],
    "2021": [
      {
        "language": "C",
        "avg_salary": 215416.4375,
        "execution_model": "compiled",
        "memory_management": "manual",
        "used": 0.048295454545454544,
        "interested": 0.03152364273204904
      },
      {
        "language": "C#",
        "avg_salary": 173039.6329113924,
        "execution_model": "compiled",
        "memory_management": "gc",
        "used": 0.10085227272727272,
        "interested": 0.0840630472854641
      },
      {
        "language": "C++",
        "avg_salary": 165702.26315789475,
        "execution_model": "compiled",
        "memory_management": "manual",
        "used": 0.07670454545454546,
        "interested": 0.06129597197898424
      },
      {
        "language": "Clojure",
        "avg_salary": 88948.0,
        "execution_model": "interpreted",
        "memory_management": "gc",
        "used": 0.004261363636363636,
        "interested": 0.008756567425569177
      },
      {
        "language": "Dart",
        "avg_salary": 127684.375,
        "execution_model": "compiled",
        "memory_management": "gc",
        "used": 0.009943181818181818,
        "interested": 0.02626970227670753
      },
      {
        "language": "F#",
        "avg_salary": 111300.0,
        "execution_model": "compiled",
        "memory_management": "gc",
        "used": 0.002840909090909091,
        "interested": 0.005253940455341506
      },
      {
        "language": "Go",
        "avg_salary": 136995.26666666666,
        "execution_model": "compiled",
        "memory_management": "gc",
        "used": 0.036931818181818184,
        "interested": 0.07880910683012259
      },
      {
        "language": "Haskell",
        "avg_salary": 120052.0,
        "execution_model": "compiled",
        "memory_management": "gc",
        "used": 0.002840909090909091,
        "interested": 0.012259194395796848
      },
      {
        "language": "Java",
        "avg_salary": 130313.06756756757,
        "execution_model": "compiled",
        "memory_management": "gc",
        "used": 0.09801136363636363,
        "interested": 0.07705779334500876
      },
      {
        "language": "JavaScript",
        "avg_salary": 141369.52662721893,
        "execution_model": "interpreted",
        "memory_management": "gc",
        "used": 0.2002840909090909,
        "interested": 0.19264448336252188
      },
      {
        "language": "Objective-C",
        "avg_salary": 130884.0,
        "execution_model": "compiled",
        "memory_management": "manual",
        "used": 0.005681818181818182,
        "interested": 0.0
      },
      {
        "language": "PHP",
        "avg_salary": 120268.68421052632,
        "execution_model": "interpreted",
        "memory_management": "gc",
        "used": 0.03551136363636364,
        "interested": 0.028021015761821366
      },
      {
        "language": "Perl",
        "avg_salary": 136819.2,
        "execution_model": "interpreted",
        "memory_management": "gc",
        "used": 0.007102272727272727,
        "interested": 0.0035026269702276708
      },
      {
        "language": "Python",
        "avg_salary": 146860.71527777778,
        "execution_model": "interpreted",
        "memory_management": "gc",
        "used": 0.16477272727272727,
        "interested": 0.17162872154115585
      },
      {
        "language": "R",
        "avg_salary": 137933.81818181818,
        "execution_model": "interpreted",
        "memory_management": "gc",
        "used": 0.011363636363636364,
        "interested": 0.014010507880910683
      },
      {
        "language": "Ruby",
        "avg_salary": 128322.61538461539,
        "execution_model": "interpreted",
        "memory_management": "gc",
        "used": 0.015625,
        "interested": 0.014010507880910683
      },
      {
        "language": "Rust",
        "avg_salary": 180318.25806451612,
        "execution_model": "compiled",
        "memory_management": "manual",
        "used": 0.015625,
        "interested": 0.0542907180385289
      },
      {
        "language": "SQL",
        "avg_salary": 136696.94949494948,
        "execution_model": "interpreted",
        "memory_management": "na",
        "used": 0.13068181818181818,
        "interested": 0.09632224168126094
      },
      {
        "language": "Scala",
        "avg_salary": 147596.53333333333,
        "execution_model": "compiled",
        "memory_management": "gc",
        "used": 0.018465909090909092,
        "interested": 0.02276707530647986
      },
      {
        "language": "Swift",
        "avg_salary": 174483.83333333334,
        "execution_model": "compiled",
        "memory_management": "gc",
        "used": 0.014204545454545454,
        "interested": 0.017513134851138354
      }
    ],
    "2022": [
      {
        "language": "C",
        "avg_salary": 131931.3103448276,
        "execution_model": "compiled",
        "memory_management": "manual",
        "used": 0.04723127035830619,
        "interested": 0.03941908713692946
      },
      {
        "language": "C#",
        "avg_salary": 203326.15,
        "execution_model": "compiled",
        "memory_management": "gc",
        "used": 0.08794788273615635,
        "interested": 0.08506224066390042
      },
      {
        "language": "C++",
        "avg_salary": 227660.875,
        "execution_model": "compiled",
        "memory_management": "manual",
        "used": 0.06188925081433225,
        "interested": 0.058091286307053944
      },
      {
        "language": "Clojure",
        "avg_salary": -1.0,
        "execution_model": "interpreted",
        "memory_management": "gc",
        "used": 0.0016286644951140066,
        "interested": 0.006224066390041493
      },
      {
        "language": "Dart",
        "avg_salary": 159409.875,
        "execution_model": "compiled",
        "memory_management": "gc",
        "used": 0.011400651465798045,
        "interested": 0.016597510373443983
      },
      {
        "language": "F#",
        "avg_salary": 114786.0,
        "execution_model": "compiled",
        "memory_management": "gc",
        "used": 0.0,
        "interested": 0.004149377593360996
      },
      {
        "language": "Go",
        "avg_salary": 148315.15151515152,
        "execution_model": "compiled",
        "memory_management": "gc",
        "used": 0.03745928338762215,
        "interested": 0.06431535269709543
      },
      {
        "language": "Haskell",
        "avg_salary": 147110.375,
        "execution_model": "compiled",
        "memory_management": "gc",
        "used": 0.004885993485342019,
        "interested": 0.016597510373443983
      },
      {
        "language": "Java",
        "avg_salary": 218765.05555555556,
        "execution_model": "compiled",
        "memory_management": "gc",
        "used": 0.09771986970684039,
        "interested": 0.06224066390041494
      },
      {
        "language": "JavaScript",
        "avg_salary": 161926.3816793893,
        "execution_model": "interpreted",
        "memory_management": "gc",
        "used": 0.21009771986970685,
        "interested": 0.18672199170124482
      },
      {
        "language": "Objective-C",
        "avg_salary": 161420.0,
        "execution_model": "compiled",
        "memory_management": "manual",
        "used": 0.014657980456026058,
        "interested": 0.004149377593360996
      },
      {
        "language": "PHP",
        "avg_salary": 102632.0,
        "execution_model": "interpreted",
        "memory_management": "gc",
        "used": 0.035830618892508145,
        "interested": 0.024896265560165973
      },
      {
        "language": "Perl",
        "avg_salary": 121963.5,
        "execution_model": "interpreted",
        "memory_management": "gc",
        "used": 0.009771986970684038,
        "interested": 0.006224066390041493
      },
      {
        "language": "Python",
        "avg_salary": 190801.6037735849,
        "execution_model": "interpreted",
        "memory_management": "gc",
        "used": 0.16775244299674266,
        "interested": 0.17842323651452283
      },
      {
        "language": "R",
        "avg_salary": 166208.0,
        "execution_model": "interpreted",
        "memory_management": "gc",
        "used": 0.013029315960912053,
        "interested": 0.01037344398340249
      },
      {
        "language": "Ruby",
        "avg_salary": 143324.55555555556,
        "execution_model": "interpreted",
        "memory_management": "gc",
        "used": 0.026058631921824105,
        "interested": 0.024896265560165973
      },
      {
        "language": "Rust",
        "avg_salary": 153963.9,
        "execution_model": "compiled",
        "memory_management": "manual",
        "used": 0.014657980456026058,
        "interested": 0.06224066390041494
      },
      {
        "language": "SQL",
        "avg_salary": 183287.67073170733,
        "execution_model": "interpreted",
        "memory_management": "na",
        "used": 0.11889250814332247,
        "interested": 0.10580912863070539
      },
      {
        "language": "Scala",
        "avg_salary": 247213.38888888888,
        "execution_model": "compiled",
        "memory_management": "gc",
        "used": 0.026058631921824105,
        "interested": 0.029045643153526972
      },
      {
        "language": "Swift",
        "avg_salary": 126526.90909090909,
        "execution_model": "compiled",
        "memory_management": "gc",
        "used": 0.013029315960912053,
        "interested": 0.014522821576763486
      }
    ],
    "2023": [
      {
        "language": "C",
        "avg_salary": 140789.25,
        "execution_model": "compiled",
        "memory_management": "manual",
        "used": 0.028645833333333332,
        "interested": 0.0182648401826484
      },
      {
        "language": "C#",
        "avg_salary": 117509.91891891892,
        "execution_model": "compiled",
        "memory_management": "gc",
        "used": 0.0859375,
        "interested": 0.0837138508371385
      },
      {
        "language": "C++",
        "avg_salary": 139283.73913043478,
        "execution_model": "compiled",
        "memory_management": "manual",
        "used": 0.05859375,
        "interested": 0.045662100456621
      },
      {
        "language": "Clojure",
        "avg_salary": 131367.75,
        "execution_model": "interpreted",
        "memory_management": "gc",
        "used": 0.0026041666666666665,
        "interested": 0.0091324200913242
      },
      {
        "language": "Dart",
        "avg_salary": 96594.8,
        "execution_model": "compiled",
        "memory_management": "gc",
        "used": 0.013020833333333334,
        "interested": 0.0121765601217656
      },
      {
        "language": "F#",
        "avg_salary": 80184.0,
        "execution_model": "compiled",
        "memory_management": "gc",
        "used": 0.0,
        "interested": 0.0015220700152207
      },
      {
        "language": "Go",
        "avg_salary": 131536.64705882352,
        "execution_model": "compiled",
        "memory_management": "gc",
        "used": 0.053385416666666664,
        "interested": 0.1050228310502283
      },
      {
        "language": "Haskell",
        "avg_salary": 94616.85714285714,
        "execution_model": "compiled",
        "memory_management": "gc",
        "used": 0.00390625,
        "interested": 0.0091324200913242
      },
      {
        "language": "Java",
        "avg_salary": 125920.07142857143,
        "execution_model": "compiled",
        "memory_management": "gc",
        "used": 0.08984375,
        "interested": 0.0593607305936073
      },
      {
        "language": "JavaScript",
        "avg_salary": 124777.54545454546,
        "execution_model": "interpreted",
        "memory_management": "gc",
        "used": 0.21744791666666666,
        "interested": 0.1750380517503805
      },
      {
        "language": "Objective-C",
        "avg_salary": 128828.8,
        "execution_model": "compiled",
        "memory_management": "manual",
        "used": 0.009114583333333334,
        "interested": 0.0015220700152207
      },
      {
        "language": "PHP",
        "avg_salary": 114409.85,
        "execution_model": "interpreted",
        "memory_management": "gc",
        "used": 0.028645833333333332,
        "interested": 0.015220700152207
      },
      {
        "language": "Perl",
        "avg_salary": 92402.14285714286,
        "execution_model": "interpreted",
        "memory_management": "gc",
        "used": 0.006510416666666667,
        "interested": 0.0030441400304414
      },
      {
        "language": "Python",
        "avg_salary": 131095.2087912088,
        "execution_model": "interpreted",
        "memory_management": "gc",
        "used": 0.1953125,
        "interested": 0.2070015220700152
      },
      {
        "language": "R",
        "avg_salary": 138221.2857142857,
        "execution_model": "interpreted",
        "memory_management": "gc",
        "used": 0.005208333333333333,
        "interested": 0.0076103500761035
      },
      {
        "language": "Ruby",
        "avg_salary": 112203.77777777778,
        "execution_model": "interpreted",
        "memory_management": "gc",
        "used": 0.006510416666666667,
        "interested": 0.0106544901065449
      },
      {
        "language": "Rust",
        "avg_salary": 143895.60714285713,
        "execution_model": "compiled",
        "memory_management": "manual",
        "used": 0.01953125,
        "interested": 0.0928462709284627
      },
      {
        "language": "SQL",
        "avg_salary": 130785.9262295082,
        "execution_model": "interpreted",
        "memory_management": "na",
        "used": 0.1484375,
        "interested": 0.1126331811263318
      },
      {
        "language": "Scala",
        "avg_salary": 131501.0588235294,
        "execution_model": "compiled",
        "memory_management": "gc",
        "used": 0.018229166666666668,
        "interested": 0.0213089802130898
      },
      {
        "language": "Swift",
        "avg_salary": 125193.8,
        "execution_model": "compiled",
        "memory_management": "gc",
        "used": 0.009114583333333334,
        "interested": 0.0091324200913242
      }
    ],
    "2024": [
      {
        "language": "C",
        "avg_salary": 118040.22222222222,
        "execution_model": "compiled",
        "memory_management": "manual",
        "used": 0.05465587044534413,
        "interested": 0.05263157894736842
      },
      {
        "language": "C#",
        "avg_salary": 116307.54761904762,
        "execution_model": "compiled",
        "memory_management": "gc",
        "used": 0.08299595141700405,
        "interested": 0.08851674641148326
      },
      {
        "language": "C++",
        "avg_salary": 124387.90322580645,
        "execution_model": "compiled",
        "memory_management": "manual",
        "used": 0.06477732793522267,
        "interested": 0.05980861244019139
      },
      {
        "language": "Clojure",
        "avg_salary": 105238.5,
        "execution_model": "interpreted",
        "memory_management": "gc",
        "used": 0.004048582995951417,
        "interested": 0.007177033492822967
      },
      {
        "language": "Dart",
        "avg_salary": 118663.0,
        "execution_model": "compiled",
        "memory_management": "gc",
        "used": 0.010121457489878543,
        "interested": 0.009569377990430622
      },
      {
        "language": "F#",
        "avg_salary": 183493.0,
        "execution_model": "compiled",
        "memory_management": "gc",
        "used": 0.0,
        "interested": 0.0023923444976076554
      },
      {
        "language": "Go",
        "avg_salary": 136264.65,
        "execution_model": "compiled",
        "memory_management": "gc",
        "used": 0.048582995951417005,
        "interested": 0.11004784688995216
      },
      {
        "language": "Haskell",
        "avg_salary": 161905.0,
        "execution_model": "compiled",
        "memory_management": "gc",
        "used": 0.0020242914979757085,
        "interested": 0.004784688995215311
      },
      {
        "language": "Java",
        "avg_salary": 134140.4814814815,
        "execution_model": "compiled",
        "memory_management": "gc",
        "used": 0.08097165991902834,
        "interested": 0.05263157894736842
      },
      {
        "language": "JavaScript",
        "avg_salary": 123030.01123595505,
        "execution_model": "interpreted",
        "memory_management": "gc",
        "used": 0.20242914979757085,
        "interested": 0.1722488038277512
      },
      {
        "language": "Objective-C",
        "avg_salary": 158307.33333333334,
        "execution_model": "compiled",
        "memory_management": "manual",
        "used": 0.008097165991902834,
        "interested": 0.0023923444976076554
      },
      {
        "language": "PHP",
        "avg_salary": 133155.4375,
        "execution_model": "interpreted",
        "memory_management": "gc",
        "used": 0.04048582995951417,
        "interested": 0.0215311004784689
      },
      {
        "language": "Perl",
        "avg_salary": 71958.0,
        "execution_model": "interpreted",
        "memory_management": "gc",
        "used": 0.006072874493927126,
        "interested": 0.0
      },
      {
        "language": "Python",
        "avg_salary": 155926.67045454544,
        "execution_model": "interpreted",
        "memory_management": "gc",
        "used": 0.18421052631578946,
        "interested": 0.1722488038277512
      },
      {
        "language": "R",
        "avg_salary": 97143.0,
        "execution_model": "interpreted",
        "memory_management": "gc",
        "used": 0.0020242914979757085,
        "interested": 0.0
      },
      {
        "language": "Ruby",
        "avg_salary": 119330.33333333333,
        "execution_model": "interpreted",
        "memory_management": "gc",
        "used": 0.01417004048582996,
        "interested": 0.01674641148325359
      },
      {
        "language": "Rust",
        "avg_salary": 141593.1923076923,
        "execution_model": "compiled",
        "memory_management": "manual",
        "used": 0.010121457489878543,
        "interested": 0.09330143540669857
      },
      {
        "language": "SQL",
        "avg_salary": 146805.68656716417,
        "execution_model": "interpreted",
        "memory_management": "na",
        "used": 0.15587044534412955,
        "interested": 0.09808612440191387
      },
      {
        "language": "Scala",
        "avg_salary": 129530.6,
        "execution_model": "compiled",
        "memory_management": "gc",
        "used": 0.022267206477732792,
        "interested": 0.0215311004784689
      },
      {
        "language": "Swift",
        "avg_salary": 131323.16666666666,
        "execution_model": "compiled",
        "memory_management": "gc",
        "used": 0.006072874493927126,
        "interested": 0.014354066985645933
      }
    ]
  }
}