{
  "country": "Belgium",
  "age": "45-54 years old",
  "max_used": 0.21428571428571427,
  "max_interested": 0.20689655172413793,
  "years": {
    "2018": [
      {
        "language": "C",
        "avg_salary": 65415.5,
        "execution_model": "compiled",
        "memory_management": "manual",
        "used": 0.07526881720430108,
        "interested": 0.039473684210526314
      },
      {
        "language": "C#",
        "avg_salary": 79144.16666666667,
        "execution_model": "compiled",
        "memory_management": "gc",
        "used": 0.11827956989247312,
        "interested": 0.13157894736842105
      },
      {
        "language": "C++",
        "avg_salary": 97297.5,
        "execution_model": "compiled",
        "memory_management": "manual",
        "used": 0.06451612903225806,
        "interested": 0.06578947368421052
      },
      {
        "language": "Clojure",
        "avg_salary": 97910.0,
        "execution_model": "interpreted",
        "memory_management": "gc",
        "used": 0.010752688172043012,
        "interested": 0.0
      },
      {
        "language": "CoffeeScript",
        "avg_salary": -1.0,
        "execution_model": "interpreted",
        "memory_management": "gc",
        "used": 0.010752688172043012,
        "interested": 0.0
      },
      {
        "language": "F#",
        "avg_salary": -1.0,
        "execution_model": "compiled",
        "memory_management": "gc",
        "used": 0.0,
        "interested": 0.013157894736842105
      },
      {
        "language": "Go",
        "avg_salary": 114228.66666666667,
        "execution_model": "compiled",
        "memory_management": "gc",
        "used": 0.021505376344086023,
        "interested": 0.07894736842105263
      },
      {
        "language": "Haskell",
        "avg_salary": 97910.0,
        "execution_model": "compiled",
        "memory_management": "gc",
        "used": 0.0,
        "interested": 0.013157894736842105
      },
      {
        "language": "Java",
        "avg_salary": 61680.0,
        "execution_model": "compiled",
        "memory_management": "gc",
        "used": 0.0967741935483871,
        "interested": 0.07894736842105263
      },
      {
        "language": "JavaScript",
        "avg_salary": 81325.83333333333,
        "execution_model": "interpreted",
        "memory_management": "gc",
        "used": 0.16129032258064516,
        "interested": 0.15789473684210525
      },
      {
        "language": "Objective-C",
        "avg_salary": 64292.0,
        "execution_model": "compiled",
        "memory_management": "manual",
        "used": 0.021505376344086023,
        "interested": 0.013157894736842105
      },
      {
        "language": "PHP",
        "avg_salary": 51856.28571428572,
        "execution_model": "interpreted",
        "memory_management": "gc",
        "used": 0.10752688172043011,
        "interested": 0.07894736842105263
      },
      {
        "language": "Perl",
        "avg_salary": 35244.0,
        "execution_model": "interpreted",
        "memory_management": "gc",
        "used": 0.010752688172043012,
        "interested": 0.0
      },
      {
        "language": "Python",
        "avg_salary": 59793.42857142857,
        "execution_model": "interpreted",
        "memory_management": "gc",
        "used": 0.08602150537634409,
        "interested": 0.07894736842105263
      },
      {
        "language": "Ruby",
        "avg_salary": 44064.0,
        "execution_model": "interpreted",
        "memory_management": "gc",
        "used": 0.010752688172043012,
        "interested": 0.0
      },
      {
        "language": "Rust",
        "avg_salary": -1.0,
        "execution_model": "compiled",
        "memory_management": "manual",
        "used": 0.0,
        "interested": 0.013157894736842105
      },
      {
        "language": "SQL",
        "avg_salary": 71378.76923076923,
        "execution_model": "interpreted",
        "memory_management": "na",
        "used": 0.17204301075268819,
        "interested": 0.18421052631578946
      },
      {
        "language": "Swift",
        "avg_salary": 83613.6,
        "execution_model": "compiled",
        "memory_management": "gc",
        "used": 0.03225806451612903,
        "interested": 0.05263157894736842
      }
    ],
    "2019": [
      {
        "language": "C",
        "avg_salary": 100430.85714285714,
        "execution_model": "compiled",
        "memory_management": "manual",
        "used": 0.06796116504854369,
        "interested": 0.04597701149425287
      },
      {
        "language": "C#",
        "avg_salary": 56166.0,
        "execution_model": "compiled",
        "memory_management": "gc",
        "used": 0.05825242718446602,
        "interested": 0.06896551724137931
      },
      {
        "language": "C++",
        "avg_salary": 100430.85714285714,
        "execution_model": "compiled",
        "memory_management": "manual",
        "used": 0.07766990291262135,
        "interested": 0.09195402298850575
      },
      {
        "language": "Go",
        "avg_salary": -1.0,
        "execution_model": "compiled",
        "memory_management": "gc",
        "used": 0.0,
        "interested": 0.011494252873563218
      },
      {
        "language": "Java",
        "avg_salary": 134844.22222222222,
        "execution_model": "compiled",
        "memory_management": "gc",
        "used": 0.10679611650485436,
        "interested": 0.09195402298850575
      },
      {
        "language": "JavaScript",
        "avg_salary": 51787.0,
        "execution_model": "interpreted",
        "memory_management": "gc",
        "used": 0.17475728155339806,
        "interested": 0.12643678160919541
      },
      {
        "language": "Objective-C",
        "avg_salary": -1.0,
        "execution_model": "compiled",
        "memory_management": "manual",
        "used": 0.0,
        "interested": 0.011494252873563218
      },
      {
        "language": "PHP",
        "avg_salary": 81117.0,
        "execution_model": "interpreted",
        "memory_management": "gc",
        "used": 0.06796116504854369,
        "interested": 0.04597701149425287
      },
      {
        "language": "Python",
        "avg_salary": 132130.3076923077,
        "execution_model": "interpreted",
        "memory_management": "gc",
        "used": 0.14563106796116504,
        "interested": 0.16091954022988506
      },
      {
        "language": "R",
        "avg_salary": 206232.0,
        "execution_model": "interpreted",
        "memory_management": "gc",
        "used": 0.038834951456310676,
        "interested": 0.022988505747126436
      },
      {
        "language": "Ruby",
        "avg_salary": -1.0,
        "execution_model": "interpreted",
        "memory_management": "gc",
        "used": 0.0,
        "interested": 0.011494252873563218
      },
      {
        "language": "Rust",
        "avg_salary": 27492.0,
        "execution_model": "compiled",
        "memory_management": "manual",
        "used": 0.019417475728155338,
        "interested": 0.04597701149425287
      },
      {
        "language": "SQL",
        "avg_salary": 96681.21739130435,
        "execution_model": "interpreted",
        "memory_management": "na",
        "used": 0.21359223300970873,
        "interested": 0.20689655172413793
      },
      {
        "language": "Scala",
        "avg_salary": 206233.0,
        "execution_model": "compiled",
        "memory_management": "gc",
        "used": 0.02912621359223301,
        "interested": 0.034482758620689655
      },
      {
        "language": "Swift",
        "avg_salary": -1.0,
        "execution_model": "compiled",
        "memory_management": "gc",
        "used": 0.0,
        "interested": 0.022988505747126436
      }
    ],
    "2020": [
      {
        "language": "C",
        "avg_salary": 111701.0,
        "execution_model": "compiled",
        "memory_management": "manual",
        "used": 0.06666666666666667,
        "interested": 0.061224489795918366
      },
      {
        "language": "C#",
        "avg_salary": 133321.0,
        "execution_model": "compiled",
        "memory_management": "gc",
        "used": 0.1111111111111111,
        "interested": 0.14285714285714285
      },
      {
        "language": "C++",
        "avg_salary": 122511.0,
        "execution_model": "compiled",
        "memory_management": "manual",
        "used": 0.1111111111111111,
        "interested": 0.12244897959183673
      },
      {
        "language": "Dart",
        "avg_salary": -1.0,
        "execution_model": "compiled",
        "memory_management": "gc",
        "used": 0.0,
        "interested": 0.04081632653061224
      },
      {
        "language": "Go",
        "avg_salary": 178361.5,
        "execution_model": "compiled",
        "memory_management": "gc",
        "used": 0.0,
        "interested": 0.061224489795918366
      },
      {
        "language": "Java",
        "avg_salary": 140527.0,
        "execution_model": "compiled",
        "memory_management": "gc",
        "used": 0.08888888888888889,
        "interested": 0.04081632653061224
      },
      {
        "language": "JavaScript",
        "avg_salary": 120318.0,
        "execution_model": "interpreted",
        "memory_management": "gc",
        "used": 0.2,
        "interested": 0.08163265306122448
      },
      {
        "language": "Perl",
        "avg_salary": 73320.0,
        "execution_model": "interpreted",
        "memory_management": "gc",
        "used": 0.022222222222222223,
        "interested": 0.02040816326530612
      },
      {
        "language": "Python",
        "avg_salary": 110213.25,
        "execution_model": "interpreted",
        "memory_management": "gc",
        "used": 0.15555555555555556,
        "interested": 0.14285714285714285
      },
      {
        "language": "R",
        "avg_salary": -1.0,
        "execution_model": "interpreted",
        "memory_management": "gc",
        "used": 0.022222222222222223,
        "interested": 0.0
      },
      {
        "language": "Ruby",
        "avg_salary": 140527.0,
        "execution_model": "interpreted",
        "memory_management": "gc",
        "used": 0.0,
        "interested": 0.02040816326530612
      },
      {
        "language": "Rust",
        "avg_salary": 118907.5,
        "execution_model": "compiled",
        "memory_management": "manual",
        "used": 0.0,
        "interested": 0.04081632653061224
      },
      {
        "language": "SQL",
        "avg_salary": 139086.0,
        "execution_model": "interpreted",
        "memory_management": "na",
        "used": 0.2,
        "interested": 0.16326530612244897
      },
      {
        "language": "Scala",
        "avg_salary": 178361.5,
        "execution_model": "compiled",
        "memory_management": "gc",
        "used": 0.022222222222222223,
        "interested": 0.02040816326530612
      },
      {
        "language": "Swift",
        "avg_salary": 140527.0,
        "execution_model": "compiled",
        "memory_management": "gc",
        "used": 0.0,
        "interested": 0.04081632653061224
      }
    ],
    "2021": [
      {
        "language": "C",
        "avg_salary": 96639.0,
        "execution_model": "compiled",
        "memory_management": "manual",
        "used": 0.05421686746987952,
        "interested": 0.04666666666666667
      },
      {
        "language": "C#",
        "avg_salary": 80798.65625,
        "execution_model": "compiled",
        "memory_management": "gc",
        "used": 0.14457831325301204,
        "interested": 0.14
      },
      {
        "language": "C++",
        "avg_salary": 71112.85714285714,
        "execution_model": "compiled",
        "memory_management": "manual",
        "used": 0.07228915662650602,
        "interested": 0.06666666666666667
      },
      {
        "language": "Clojure",
        "avg_salary": -1.0,
        "execution_model": "interpreted",
        "memory_management": "gc",
        "used": 0.006024096385542169,
        "interested": 0.006666666666666667
      },
      {
        "language": "Dart",
        "avg_salary": 109827.6,
        "execution_model": "compiled",
        "memory_management": "gc",
        "used": 0.012048192771084338,
        "interested": 0.02
      },
      {
        "language": "F#",
        "avg_salary": 44861.0,
        "execution_model": "compiled",
        "memory_management": "gc",
        "used": 0.0,
        "interested": 0.013333333333333334
      },
      {
        "language": "Go",
        "avg_salary": 104638.6,
        "execution_model": "compiled",
        "memory_management": "gc",
        "used": 0.018072289156626505,
        "interested": 0.013333333333333334
      },
      {
        "language": "Haskell",
        "avg_salary": -1.0,
        "execution_model": "compiled",
        "memory_management": "gc",
        "used": 0.0,
        "interested": 0.006666666666666667
      },
      {
        "language": "Java",
        "avg_salary": 107487.23529411765,
        "execution_model": "compiled",
        "memory_management": "gc",
        "used": 0.0963855421686747,
        "interested": 0.07333333333333333
      },
      {
        "language": "JavaScript",
        "avg_salary": 93165.23076923077,
        "execution_model": "interpreted",
        "memory_management": "gc",
        "used": 0.18072289156626506,
        "interested": 0.18
      },
      {
        "language": "Objective-C",
        "avg_salary": -1.0,
        "execution_model": "compiled",
        "memory_management": "manual",
        "used": 0.012048192771084338,
        "interested": 0.013333333333333334
      },
      {
        "language": "PHP",
        "avg_salary": 81964.125,
        "execution_model": "interpreted",
        "memory_management": "gc",
        "used": 0.05421686746987952,
        "interested": 0.02
      },
      {
        "language": "Perl",
        "avg_salary": 105933.5,
        "execution_model": "interpreted",
        "memory_management": "gc",
        "used": 0.012048192771084338,
        "interested": 0.0
      },
      {
        "language": "Python",
        "avg_salary": 86667.125,
        "execution_model": "interpreted",
        "memory_management": "gc",
        "used": 0.08433734939759036,
        "interested": 0.11333333333333333
      },
      {
        "language": "R",
        "avg_salary": 101502.0,
        "execution_model": "interpreted",
        "memory_management": "gc",
        "used": 0.018072289156626505,
        "interested": 0.02
      },
      {
        "language": "Ruby",
        "avg_salary": 64859.0,
        "execution_model": "interpreted",
        "memory_management": "gc",
        "used": 0.012048192771084338,
        "interested": 0.013333333333333334
      },
      {
        "language": "Rust",
        "avg_salary": 93458.42857142857,
        "execution_model": "compiled",
        "memory_management": "manual",
        "used": 0.006024096385542169,
        "interested": 0.05333333333333334
      },
      {
        "language": "SQL",
        "avg_salary": 86360.56756756757,
        "execution_model": "interpreted",
        "memory_management": "na",
        "used": 0.20481927710843373,
        "interested": 0.15333333333333332
      },
      {
        "language": "Scala",
        "avg_salary": 96964.0,
        "execution_model": "compiled",
        "memory_management": "gc",
        "used": 0.006024096385542169,
        "interested": 0.02666666666666667
      },
      {
        "language": "Swift",
        "avg_salary": -1.0,
        "execution_model": "compiled",
        "memory_management": "gc",
        "used": 0.006024096385542169,
        "interested": 0.02
      }
    ],
    "2022": [
      {
        "language": "C",
        "avg_salary": 63901.6,
        "execution_model": "compiled",
        "memory_management": "manual",
        "used": 0.05194805194805195,
        "interested": 0.027522935779816515
      },
      {
        "language": "C#",
        "avg_salary": 163632.125,
        "execution_model": "compiled",
        "memory_management": "gc",
        "used": 0.1038961038961039,
        "interested": 0.1559633027522936
      },
      {
        "language": "C++",
        "avg_salary": 85230.4,
        "execution_model": "compiled",
        "memory_management": "manual",
        "used": 0.05844155844155844,
        "interested": 0.05504587155963303
      },
      {
        "language": "Clojure",
        "avg_salary": -1.0,
        "execution_model": "interpreted",
        "memory_management": "gc",
        "used": 0.0,
        "interested": 0.01834862385321101
      },
      {
        "language": "Dart",
        "avg_salary": -1.0,
        "execution_model": "compiled",
        "memory_management": "gc",
        "used": 0.012987012987012988,
        "interested": 0.009174311926605505
      },
      {
        "language": "F#",
        "avg_salary": 51192.0,
        "execution_model": "compiled",
        "memory_management": "gc",
        "used": 0.006493506493506494,
        "interested": 0.01834862385321101
      },
      {
        "language": "Go",
        "avg_salary": 76783.0,
        "execution_model": "compiled",
        "memory_management": "gc",
        "used": 0.025974025974025976,
        "interested": 0.027522935779816515
      },
      {
        "language": "Haskell",
        "avg_salary": 55032.0,
        "execution_model": "compiled",
        "memory_management": "gc",
        "used": 0.0,
        "interested": 0.01834862385321101
      },
      {
        "language": "Java",
        "avg_salary": 277487.8,
        "execution_model": "compiled",
        "memory_management": "gc",
        "used": 0.09740259740259741,
        "interested": 0.06422018348623854
      },
      {
        "language": "JavaScript",
        "avg_salary": 148671.66666666666,
        "execution_model": "interpreted",
        "memory_management": "gc",
        "used": 0.17532467532467533,
        "interested": 0.11926605504587157
      },
      {
        "language": "Objective-C",
        "avg_salary": 49056.0,
        "execution_model": "compiled",
        "memory_management": "manual",
        "used": 0.006493506493506494,
        "interested": 0.0
      },
      {
        "language": "PHP",
        "avg_salary": 209021.85714285713,
        "execution_model": "interpreted",
        "memory_management": "gc",
        "used": 0.05844155844155844,
        "interested": 0.01834862385321101
      },
      {
        "language": "Perl",
        "avg_salary": 349792.6666666667,
        "execution_model": "interpreted",
        "memory_management": "gc",
        "used": 0.025974025974025976,
        "interested": 0.01834862385321101
      },
      {
        "language": "Python",
        "avg_salary": 182642.61538461538,
        "execution_model": "interpreted",
        "memory_management": "gc",
        "used": 0.1038961038961039,
        "interested": 0.11009174311926606
      },
      {
        "language": "R",
        "avg_salary": 501388.0,
        "execution_model": "interpreted",
        "memory_management": "gc",
        "used": 0.012987012987012988,
        "interested": 0.027522935779816515
      },
      {
        "language": "Ruby",
        "avg_salary": 114461.0,
        "execution_model": "interpreted",
        "memory_management": "gc",
        "used": 0.012987012987012988,
        "interested": 0.01834862385321101
      },
      {
        "language": "Rust",
        "avg_salary": 79609.25,
        "execution_model": "compiled",
        "memory_management": "manual",
        "used": 0.006493506493506494,
        "interested": 0.06422018348623854
      },
      {
        "language": "SQL",
        "avg_salary": 196686.4516129032,
        "execution_model": "interpreted",
        "memory_management": "na",
        "used": 0.21428571428571427,
        "interested": 0.2018348623853211
      },
      {
        "language": "Scala",
        "avg_salary": -1.0,
        "execution_model": "compiled",
        "memory_management": "gc",
        "used": 0.012987012987012988,
        "interested": 0.0
      },
      {
        "language": "Swift",
        "avg_salary": 77137.33333333333,
        "execution_model": "compiled",
        "memory_management": "gc",
        "used": 0.012987012987012988,
        "interested": 0.027522935779816515
      }
    ],
    "2023": [
      {
        "language": "C",
        "avg_salary": 72055.85714285714,
        "execution_model": "compiled",
        "memory_management": "manual",
        "used": 0.03731343283582089,
        "interested": 0.02843601895734597
      },
      {
        "language": "C#",
        "avg_salary": 92882.43333333333,
        "execution_model": "compiled",
        "memory_management": "gc",
        "used": 0.10820895522388059,
        "interested": 0.10900473933649289
      },
      {
        "language": "C++",
        "avg_salary": 88349.125,
        "execution_model": "compiled",
        "memory_management": "manual",
        "used": 0.05223880597014925,
        "interested": 0.037914691943127965
      },
      {
        "language": "Clojure",
        "avg_salary": 64254.0,
        "execution_model": "interpreted",
        "memory_management": "gc",
        "used": 0.0,
        "interested": 0.009478672985781991
      },
      {
        "language": "Dart",
        "avg_salary": 64254.0,
        "execution_model": "compiled",
        "memory_management": "gc",
        "used": 0.007462686567164179,
        "interested": 0.009478672985781991
      },
      {
        "language": "F#",
        "avg_salary": 82994.5,
        "execution_model": "compiled",
        "memory_management": "gc",
        "used": 0.0037313432835820895,
        "interested": 0.018957345971563982
      },
      {
        "language": "Go",
        "avg_salary": 131720.2,
        "execution_model": "compiled",
        "memory_management": "gc",
        "used": 0.018656716417910446,
        "interested": 0.04265402843601896
      },
      {
        "language": "Haskell",
        "avg_salary": 70679.4,
        "execution_model": "compiled",
        "memory_management": "gc",
        "used": 0.011194029850746268,
        "interested": 0.018957345971563982
      },
      {
        "language": "Java",
        "avg_salary": 105636.21428571429,
        "execution_model": "compiled",
        "memory_management": "gc",
        "used": 0.08582089552238806,
        "interested": 0.08530805687203792
      },
      {
        "language": "JavaScript",
        "avg_salary": 102322.41935483871,
        "execution_model": "interpreted",
        "memory_management": "gc",
        "used": 0.17164179104477612,
        "interested": 0.15165876777251186
      },
      {
        "language": "Objective-C",
        "avg_salary": 74963.0,
        "execution_model": "compiled",
        "memory_management": "manual",
        "used": 0.022388059701492536,
        "interested": 0.018957345971563982
      },
      {
        "language": "PHP",
        "avg_salary": 100093.0,
        "execution_model": "interpreted",
        "memory_management": "gc",
        "used": 0.07835820895522388,
        "interested": 0.04265402843601896
      },
      {
        "language": "Perl",
        "avg_salary": 160634.0,
        "execution_model": "interpreted",
        "memory_management": "gc",
        "used": 0.026119402985074626,
        "interested": 0.004739336492890996
      },
      {
        "language": "Python",
        "avg_salary": 95279.94444444444,
        "execution_model": "interpreted",
        "memory_management": "gc",
        "used": 0.13805970149253732,
        "interested": 0.14218009478672985
      },
      {
        "language": "R",
        "avg_salary": 99057.5,
        "execution_model": "interpreted",
        "memory_management": "gc",
        "used": 0.011194029850746268,
        "interested": 0.009478672985781991
      },
      {
        "language": "Ruby",
        "avg_salary": 91561.5,
        "execution_model": "interpreted",
        "memory_management": "gc",
        "used": 0.011194029850746268,
        "interested": 0.014218009478672985
      },
      {
        "language": "Rust",
        "avg_salary": 106116.0,
        "execution_model": "compiled",
        "memory_management": "manual",
        "used": 0.014925373134328358,
        "interested": 0.061611374407582936
      },
      {
        "language": "SQL",
        "avg_salary": 99130.90909090909,
        "execution_model": "interpreted",
        "memory_management": "na",
        "used": 0.17537313432835822,
        "interested": 0.15639810426540285
      },
      {
        "language": "Scala",
        "avg_salary": 64254.0,
        "execution_model": "compiled",
        "memory_management": "gc",
        "used": 0.0037313432835820895,
        "interested": 0.009478672985781991
      },
      {
        "language": "Swift",
        "avg_salary": 84333.25,
        "execution_model": "compiled",
        "memory_management": "gc",
        "used": 0.022388059701492536,
        "interested": 0.02843601895734597
      }
    ],
    "2024": [
      {
        "language": "C",
        "avg_salary": 95949.66666666667,
        "execution_model": "compiled",
        "memory_management": "manual",
        "used": 0.08898305084745763,
        "interested": 0.06486486486486487
      },
      {
        "language": "C#",
        "avg_salary": 99399.54545454546,
        "execution_model": "compiled",
        "memory_management": "gc",
        "used": 0.1016949152542373,
        "interested": 0.10810810810810811
      },
      {
        "language": "C++",
        "avg_salary": 89818.5,
        "execution_model": "compiled",
        "memory_management": "manual",
        "used": 0.08050847457627118,
        "interested": 0.07027027027027027
      },
      {
        "language": "Clojure",
        "avg_salary": 161109.0,
        "execution_model": "interpreted",
        "memory_management": "gc",
        "used": 0.00423728813559322,
        "interested": 0.0
      },
      {
        "language": "Dart",
        "avg_salary": -1.0,
        "execution_model": "compiled",
        "memory_management": "gc",
        "used": 0.00847457627118644,
        "interested": 0.005405405405405406
      },
      {
        "language": "F#",
        "avg_salary": -1.0,
        "execution_model": "compiled",
        "memory_management": "gc",
        "used": 0.00423728813559322,
        "interested": 0.010810810810810811
      },
      {
        "language": "Go",
        "avg_salary": 63101.25,
        "execution_model": "compiled",
        "memory_management": "gc",
        "used": 0.01694915254237288,
        "interested": 0.043243243243243246
      },
      {
        "language": "Haskell",
        "avg_salary": 83240.0,
        "execution_model": "compiled",
        "memory_management": "gc",
        "used": 0.00847457627118644,
        "interested": 0.010810810810810811
      },
      {
        "language": "Java",
        "avg_salary": 106332.0,
        "execution_model": "compiled",
        "memory_management": "gc",
        "used": 0.1016949152542373,
        "interested": 0.08648648648648649
      },
      {
        "language": "JavaScript",
        "avg_salary": 123047.375,
        "execution_model": "interpreted",
        "memory_management": "gc",
        "used": 0.1483050847457627,
        "interested": 0.11891891891891893
      },
      {
        "language": "Objective-C",
        "avg_salary": 80555.0,
        "execution_model": "compiled",
        "memory_management": "manual",
        "used": 0.01694915254237288,
        "interested": 0.010810810810810811
      },
      {
        "language": "PHP",
        "avg_salary": 83240.0,
        "execution_model": "interpreted",
        "memory_management": "gc",
        "used": 0.038135593220338986,
        "interested": 0.005405405405405406
      },
      {
        "language": "Perl",
        "avg_salary": -1.0,
        "execution_model": "interpreted",
        "memory_management": "gc",
        "used": 0.00423728813559322,
        "interested": 0.0
      },
      {
        "language": "Python",
        "avg_salary": 100066.91666666667,
        "execution_model": "interpreted",
        "memory_management": "gc",
        "used": 0.1271186440677966,
        "interested": 0.12972972972972974
      },
      {
        "language": "R",
        "avg_salary": 76616.33333333333,
        "execution_model": "interpreted",
        "memory_management": "gc",
        "used": 0.025423728813559324,
        "interested": 0.02702702702702703
      },
      {
        "language": "Ruby",
        "avg_salary": 57462.0,
        "execution_model": "interpreted",
        "memory_management": "gc",
        "used": 0.01694915254237288,
        "interested": 0.016216216216216217
      },
      {
        "language": "Rust",
        "avg_salary": 90988.57142857143,
        "execution_model": "compiled",
        "memory_management": "manual",
        "used": 0.0211864406779661,
        "interested": 0.10810810810810811
      },
      {
        "language": "SQL",
        "avg_salary": 129961.57142857143,
        "execution_model": "interpreted",
        "memory_management": "na",
        "used": 0.1652542372881356,
        "interested": 0.16216216216216217
      },
      {
        "language": "Scala",
        "avg_salary": 71962.0,
        "execution_model": "compiled",
        "memory_management": "gc",
        "used": 0.00423728813559322,
        "interested": 0.005405405405405406
      },
      {
        "language": "Swift",
        "avg_salary": 80555.0,
        "execution_model": "compiled",
        "memory_management": "gc",
        "used": 0.01694915254237288,
        "interested": 0.016216216216216217
      }
    ]
  }
}